taya/__init__.py
taya/runner.py
taya/wz.py
taya-2.0.dist-info/METADATA
taya-2.0.dist-info/WHEEL
taya-2.0.dist-info/entry_points.txt
taya-2.0.dist-info/top_level.txt
taya-2.0.dist-info/RECORD
