Metadata-Version: 2.4
Name: taya
Version: 2.0
Summary: Free Fire Page Hack
Home-page: https://github.com/imadoo27/taya
Author: IMAD-213
Author-email: madmadimado59@gmail.com
Classifier: Programming Language :: Python :: 3
Classifier: License :: OSI Approved :: MIT License
Classifier: Operating System :: OS Independent
Requires-Python: >=3.6
Dynamic: author
Dynamic: author-email
Dynamic: classifier
Dynamic: description
Dynamic: description-content-type
Dynamic: home-page
Dynamic: requires-python
Dynamic: summary
